.coveragerc
.mailmap
.testr.conf
AUTHORS
ChangeLog
HACKING.rst
LICENSE
MANIFEST.in
README.rst
babel.cfg
post_test_hook.sh
requirements.txt
setup.cfg
setup.py
test-requirements.txt
tox.ini
doc/Makefile
doc/build/doctrees/authentication.doctree
doc/build/doctrees/backwards-incompatible.doctree
doc/build/doctrees/command-list.doctree
doc/build/doctrees/commands.doctree
doc/build/doctrees/configuration.doctree
doc/build/doctrees/environment.pickle
doc/build/doctrees/humaninterfaceguide.doctree
doc/build/doctrees/index.doctree
doc/build/doctrees/interactive.doctree
doc/build/doctrees/plugins.doctree
doc/build/doctrees/releases.doctree
doc/build/doctrees/api/modules.doctree
doc/build/doctrees/api/openstackclient.api.doctree
doc/build/doctrees/api/openstackclient.common.doctree
doc/build/doctrees/api/openstackclient.compute.doctree
doc/build/doctrees/api/openstackclient.compute.v2.doctree
doc/build/doctrees/api/openstackclient.doctree
doc/build/doctrees/api/openstackclient.identity.doctree
doc/build/doctrees/api/openstackclient.identity.v2_0.doctree
doc/build/doctrees/api/openstackclient.identity.v3.doctree
doc/build/doctrees/api/openstackclient.image.doctree
doc/build/doctrees/api/openstackclient.image.v1.doctree
doc/build/doctrees/api/openstackclient.image.v2.doctree
doc/build/doctrees/api/openstackclient.network.doctree
doc/build/doctrees/api/openstackclient.network.v2.doctree
doc/build/doctrees/api/openstackclient.object.doctree
doc/build/doctrees/api/openstackclient.object.v1.doctree
doc/build/doctrees/api/openstackclient.tests.api.doctree
doc/build/doctrees/api/openstackclient.tests.common.doctree
doc/build/doctrees/api/openstackclient.tests.compute.doctree
doc/build/doctrees/api/openstackclient.tests.compute.v2.doctree
doc/build/doctrees/api/openstackclient.tests.doctree
doc/build/doctrees/api/openstackclient.tests.identity.doctree
doc/build/doctrees/api/openstackclient.tests.identity.v2_0.doctree
doc/build/doctrees/api/openstackclient.tests.identity.v3.doctree
uos.cli.egg-info/PKG-INFO
uos.cli.egg-info/SOURCES.txt
uos.cli.egg-info/dependency_links.txt
uos.cli.egg-info/entry_points.txt
uos.cli.egg-info/not-zip-safe
uos.cli.egg-info/pbr.json
uos.cli.egg-info/requires.txt
uos.cli.egg-info/top_level.txt